actuarydesk/__init__.py
actuarydesk/actuarial_math.py
actuarydesk/actuarial_tables.py
actuarydesk/financial_math.py
actuarydesk/math_economics_viz/__init__.py
actuarydesk/math_economics_viz/average_interest_rates_US_treasury.py
actuarydesk/math_economics_viz/federal_interest_rates_kaggle.py
actuarydesk/math_economics_viz/financial_indicators_US_stocks_kaggle.py
actuarydesk/math_economics_viz/stochastic_random_walk.py
actuarydesk/math_economics_viz/world_development_indicator_kaggle.py
actuarydesk-0.2.0.dist-info/LICENSE.txt
actuarydesk-0.2.0.dist-info/METADATA
actuarydesk-0.2.0.dist-info/WHEEL
actuarydesk-0.2.0.dist-info/top_level.txt
actuarydesk-0.2.0.dist-info/RECORD
