Metadata-Version: 2.1
Name: actuarydesk
Version: 0.2.0
Summary: Tools for actuary to model and analyze simple products or for actuarial students to practice.
Home-page: https://github.com/anbarief/actuarydesk
Author: Arief Anbiya
Author-email: anbarief@live.com
License: UNKNOWN
Platform: UNKNOWN
Classifier: Programming Language :: Python :: 3
Classifier: License :: OSI Approved :: GNU General Public License v3 (GPLv3)
Classifier: Operating System :: OS Independent
Classifier: Topic :: Scientific/Engineering :: Mathematics
Classifier: Intended Audience :: Financial and Insurance Industry
Requires-Python: >=3.6
Requires-Dist: pandas
Requires-Dist: matplotlib
Requires-Dist: sklearn
